<?xml version="1.0" encoding="UTF-8"?>
<metadata xml:lang="en"><Esri><CreaDate>20190710</CreaDate><CreaTime>10543400</CreaTime><ArcGISFormat>1.0</ArcGISFormat><SyncOnce>TRUE</SyncOnce><DataProperties><lineage><Process ToolSource="c:\program files (x86)\arcgis\desktop10.5\ArcToolbox\Toolboxes\Data Management Tools.tbx\CalculateField" Date="20190710" Time="105434">CalculateField citybuildings floor 20 VB #</Process><Process ToolSource="c:\program files (x86)\arcgis\desktop10.5\ArcToolbox\Toolboxes\Data Management Tools.tbx\CalculateField" Date="20190710" Time="105510">CalculateField citybuildings floor 30 VB #</Process><Process ToolSource="c:\program files (x86)\arcgis\desktop10.5\ArcToolbox\Toolboxes\Data Management Tools.tbx\CalculateField" Date="20190710" Time="105555">CalculateField citybuildings floor 25 VB #</Process><Process ToolSource="c:\program files (x86)\arcgis\desktop10.5\ArcToolbox\Toolboxes\Data Management Tools.tbx\CalculateField" Date="20190710" Time="105628">CalculateField citybuildings floor 15 VB #</Process><Process ToolSource="c:\program files (x86)\arcgis\desktop10.5\ArcToolbox\Toolboxes\Data Management Tools.tbx\CalculateField" Date="20190710" Time="105712">CalculateField citybuildings floor 36 VB #</Process><Process ToolSource="c:\program files (x86)\arcgis\desktop10.5\ArcToolbox\Toolboxes\Data Management Tools.tbx\CalculateField" Date="20190710" Time="105943">CalculateField citybuildings use [building] VB #</Process><Process ToolSource="c:\program files (x86)\arcgis\desktop10.5\ArcToolbox\Toolboxes\Data Management Tools.tbx\CalculateField" Date="20190710" Time="110046">CalculateField citybuildings use commercial VB #</Process><Process ToolSource="c:\program files (x86)\arcgis\desktop10.5\ArcToolbox\Toolboxes\Data Management Tools.tbx\CalculateField" Date="20190710" Time="110139">CalculateField citybuildings use "commercial" VB #</Process><Process ToolSource="c:\program files (x86)\arcgis\desktop10.5\ArcToolbox\Toolboxes\Data Management Tools.tbx\CalculateField" Date="20190710" Time="110224">CalculateField citybuildings use "government officel" VB #</Process><Process ToolSource="c:\program files (x86)\arcgis\desktop10.5\ArcToolbox\Toolboxes\Data Management Tools.tbx\CalculateField" Date="20190710" Time="110247">CalculateField citybuildings use "educationl" VB #</Process><Process ToolSource="c:\program files (x86)\arcgis\desktop10.5\ArcToolbox\Toolboxes\Data Management Tools.tbx\CalculateField" Date="20190710" Time="110309">CalculateField citybuildings use "residential" VB #</Process><Process ToolSource="c:\program files (x86)\arcgis\desktop10.5\ArcToolbox\Toolboxes\Data Management Tools.tbx\CalculateField" Date="20190710" Time="110334">CalculateField citybuildings use "not classified" VB #</Process></lineage></DataProperties></Esri></metadata>
